tasr/__init__.py
tasr/cli.py
tasr-0.1.0.dist-info/LICENSE
tasr-0.1.0.dist-info/METADATA
tasr-0.1.0.dist-info/WHEEL
tasr-0.1.0.dist-info/entry_points.txt
tasr-0.1.0.dist-info/top_level.txt
tasr-0.1.0.dist-info/RECORD
