Metadata-Version: 2.1
Name: tasr
Version: 0.1.0
Summary: A simple CLI tool focused on quickly and accurately converting audio files into text.
Home-page: https://github.com/ai-libx/transcribe-asr
Author: Chiawei Lee
Author-email: ljw@live.jp
License: Apache License v2
Platform: UNKNOWN
Classifier: Programming Language :: Python :: 3
Classifier: License :: OSI Approved :: Apache Software License
Classifier: Operating System :: OS Independent
Requires-Python: >=3.7
License-File: LICENSE
Requires-Dist: funasr>=1.2.6
Requires-Dist: setuptools>=58.1.0
Requires-Dist: soundfile>=0.13.1
